{
  "$schema": "https://json-schema.org/draft-07/schema",
  "type": "object",
  "additionalProperties": false,
  "minProperties": 1,
  "maxProperties": 1,
  "properties": {
    "meters": {
      "type": "number"
    },
    "m": {
      "type": "number"
    },
    "decimeters": {
      "type": "number"
    },
    "dm": {
      "type": "number"
    },
    "centimeters": {
      "type": "number"
    },
    "cm": {
      "type": "number"
    },
    "millimeters": {
      "type": "number"
    },
    "mm": {
      "type": "number"
    }
  }
}
